sequence_modelling/DiscreteOptim.py
sequence_modelling/__init__.py
sequence_modelling/emissionplus.py
sequence_modelling/emmissions.py
sequence_modelling/hmm.py
sequence_modelling/hmmviz.py
sequence_modelling/qdhmm.py
sequence_modelling/qdhmm_logscaled.py
sequence_modelling/utils.py
sequence_modelling-0.1.6.dist-info/LICENSE
sequence_modelling-0.1.6.dist-info/METADATA
sequence_modelling-0.1.6.dist-info/WHEEL
sequence_modelling-0.1.6.dist-info/RECORD
