Metadata-Version: 2.1
Name: sequence-modelling
Version: 0.1.6
Summary: sequence modelling using HMMs
License: BSD-2-Clause
Author: Nitin Bhushan
Author-email: bhushan.nitin@posteo.net
Requires-Python: >=3.9.0,<3.10.0
Classifier: License :: OSI Approved :: BSD License
Classifier: Programming Language :: Python :: 3
Classifier: Programming Language :: Python :: 3.9
Provides-Extra: docs
Requires-Dist: Sphinx (==4.2.0) ; extra == "docs"
Requires-Dist: numpy (>=1.24.2,<2.0.0)
Requires-Dist: pytest-cov (>=4.1.0,<5.0.0)
Requires-Dist: scipy (>=1.10.1,<2.0.0)
Requires-Dist: sphinx-rtd-theme (==1.0.0) ; extra == "docs"
Requires-Dist: sphinxcontrib-napoleon (==0.7) ; extra == "docs"
